[
  {
    "Person Code": "00x5",
    "Broker Data": "",
    "Name": "O'Shevlin,Maurits",
    "Address": "79079 Manley Center",
    "Email Addresses": ["moshevlin0@netscape.com"]
  },
  {
    "Person Code": "00x6",
    "Broker Data": "",
    "Name": "Sharrem,Leonie",
    "Address": "62464 Oneill Junction",
    "Email Addresses": [""]
  },
  {
    "Person Code": "00x7",
    "Broker Data": "",
    "Name": "Brain,Benny",
    "Address": "185 Meadow Valley Parkway",
    "Email Addresses": [""]
  },
  {
    "Person Code": "00x8",
    "Broker Data": "",
    "Name": "Avey,Georgeta",
    "Address": "28567 Independence Drive",
    "Email Addresses": ["gavey3@salon.com"]
  },
  {
    "Person Code": "00x9",
    "Broker Data": "",
    "Name": "Kidby,Alessandra",
    "Address": "00 Dayton Hill",
    "Email Addresses": ["akidby4@xrea.com"]
  },
  {
    "Person Code": "00xa",
    "Broker Data": "J",
    "Name": "Cooke,Devy",
    "Address": "9656 Arkansas Street",
    "Email Addresses": ["dcooke5@imgur.com"]
  },
  {
    "Person Code": "00xb",
    "Broker Data": "",
    "Name": "Bubeer,Ross",
    "Address": "52812 Hauk Center",
    "Email Addresses": ["rbubeer6@tmall.com"]
  },
  {
    "Person Code": "00xc",
    "Broker Data": "",
    "Name": "Strowthers,Marjory",
    "Address": "0 Tennyson Drive",
    "Email Addresses": ["mstrowthers7@amazon.co.jp","mstrowthers7@engadget.com"]
  },
  {
    "Person Code": "00xd",
    "Broker Data": "",
    "Name": "Moir,Orv",
    "Address": "3 Welch Avenue",
    "Email Addresses": ["omoir8@nymag.com"]
  },
  {
    "Person Code": "00xe",
    "Broker Data": "E",
    "Name": "Marran,Lolita",
    "Address": "78 Dryden Drive",
    "Email Addresses": [""]
  },
  {
    "Person Code": "00xf",
    "Broker Data": "",
    "Name": "Arger,Anne-corinne",
    "Address": "51877 Lindbergh Road",
    "Email Addresses": ["aargera@indiegogo.com"]
  },
  {
    "Person Code": "0x10",
    "Broker Data": "J",
    "Name": "Mount,Danette",
    "Address": "68360 Ronald Regan Lane",
    "Email Addresses": ["dmountb@mashable.com"]
  },
  {
    "Person Code": "0x11",
    "Broker Data": "",
    "Name": "Everest,Joaquin",
    "Address": "9 Elgar Center",
    "Email Addresses": ["jeverestc@cpanel.net","jeverestc@godaddy.com"]
  },
  {
    "Person Code": "0x12",
    "Broker Data": "E",
    "Name": "Bains,Aluino",
    "Address": "0157 Monica Terrace",
    "Email Addresses": ["abainsd@zdnet.com","abainsd@engadget.com"]
  },
  {
    "Person Code": "0x13",
    "Broker Data": "",
    "Name": "Simionescu,Murvyn",
    "Address": "3931 Memorial Crossing",
    "Email Addresses": [""]
  },
  {
    "Person Code": "0x14",
    "Broker Data": "E",
    "Name": "Gniewosz,Morissa",
    "Address": "81629 Darwin Parkway",
    "Email Addresses": ["mgniewoszf@livejournal.com"]
  },
  {
    "Person Code": "0x15",
    "Broker Data": "",
    "Name": "Crocket,Patrizia",
    "Address": "77 Wayridge Lane",
    "Email Addresses": ["pcrocketg@jugem.jp","pcrocketg@reference.com"]
  },
  {
    "Person Code": "0x16",
    "Broker Data": "",
    "Name": "Firmin,Barbara",
    "Address": "25 Vermont Junction",
    "Email Addresses": [""]
  },
  {
    "Person Code": "0x17",
    "Broker Data": "",
    "Name": "Simmen,Consolata",
    "Address": "9885 Novick Plaza",
    "Email Addresses": ["csimmeni@archive.org"]
  },
  {
    "Person Code": "0x18",
    "Broker Data": "",
    "Name": "Lavies,Bo",
    "Address": "3 Vahlen Point",
    "Email Addresses": ["blaviesj@ovh.net"]
  },
  {
    "Person Code": "0x19",
    "Broker Data": "",
    "Name": "Gueinn,Edin",
    "Address": "11 Cambridge Road",
    "Email Addresses": ["egueinnk@digg.com"]
  },
  {
    "Person Code": "0x1a",
    "Broker Data": "",
    "Name": "Brinkworth,Ev",
    "Address": "25133 Blue Bill Park Avenue",
    "Email Addresses": [""]
  },
  {
    "Person Code": "0x1b",
    "Broker Data": "",
    "Name": "Mattiello,Sib",
    "Address": "4783 Rieder Plaza",
    "Email Addresses": ["smattiellom@tiny.cc","smattiellom@ucoz.ru"]
  },
  {
    "Person Code": "0x1c",
    "Broker Data": "",
    "Name": "Ivanyutin,Duff",
    "Address": "67 Daystar Drive",
    "Email Addresses": ["divanyutinn@fema.gov"]
  },
  {
    "Person Code": "0x1d",
    "Broker Data": "",
    "Name": "Yoakley,Batholomew",
    "Address": "4774 Mccormick Road",
    "Email Addresses": ["byoakleyo@tumblr.com","byoakleyo@tinyurl.com"]
  },
  {
    "Person Code": "0x1e",
    "Broker Data": "",
    "Name": "Rysdale,Dick",
    "Address": "64 Forest Run Point",
    "Email Addresses": ["drysdalep@admin.charstar","drysdalep@amazon.com"]
  },
  {
    "Person Code": "0x1f",
    "Broker Data": "",
    "Name": "Pooly,Mandel",
    "Address": "779 Ramsey Trail",
    "Email Addresses": ["mpoolyq@51.charistared","mpoolyq@booking.com"]
  },
  {
    "Person Code": "0x20",
    "Broker Data": "",
    "Name": "Flamank,Eudora",
    "Address": "056 Stang Hill",
    "Email Addresses": ["eflamankr@plala.or.jp","eflamankr@walmart.com"]
  },
  {
    "Person Code": "0x21",
    "Broker Data": "",
    "Name": "Edmons,Martainn",
    "Address": "8662 Pleasure Place",
    "Email Addresses": ["medmonss@indiegogo.com"]
  },
  {
    "Person Code": "0x22",
    "Broker Data": "",
    "Name": "Tampling,Erik",
    "Address": "21065 Green Ridge Park",
    "Email Addresses": ["etamplingt@hc360.com","etamplingt@meetup.com"]
  },
  {
    "Person Code": "0x23",
    "Broker Data": "",
    "Name": "Dowrey,Marje",
    "Address": "687 Mandrake Court",
    "Email Addresses": ["mdowreyu@thetimes.co.uk"]
  },
  {
    "Person Code": "0x24",
    "Broker Data": "",
    "Name": "Blissitt,Lazar",
    "Address": "95005 Reindahl Plaza",
    "Email Addresses": ["lblissittv@g.co","lblissittv@netlog.com"]
  },
  {
    "Person Code": "0x25",
    "Broker Data": "E",
    "Name": "Braxay,Ty",
    "Address": "9 Claremont Junction",
    "Email Addresses": ["tbraxayw@house.gov","tbraxayw@sbwire.com"]
  },
  {
    "Person Code": "0x26",
    "Broker Data": "E",
    "Name": "Doleman,Katine",
    "Address": "20495 Esker Circle",
    "Email Addresses": ["kdolemanx@irs.gov","kdolemanx@fda.gov"]
  },
  {
    "Person Code": "0x27",
    "Broker Data": "E",
    "Name": "Saye,Verina",
    "Address": "2864 Parkside Drive",
    "Email Addresses": ["vsayey@yahoo.com"]
  },
  {
    "Person Code": "0x28",
    "Broker Data": "",
    "Name": "Chedgey,Christy",
    "Address": "0 Walton Park",
    "Email Addresses": ["cchedgeyz@elpais.com"]
  },
  {
    "Person Code": "0x29",
    "Broker Data": "",
    "Name": "Lasslett,Leonelle",
    "Address": "02717 Dwight Trail",
    "Email Addresses": ["llasslett10@vistaprint.com"]
  },
  {
    "Person Code": "0x2a",
    "Broker Data": "",
    "Name": "Elphinston,Brent",
    "Address": "95258 American Way",
    "Email Addresses": ["belphinston11@taobao.com","belphinston11@cbc.ca"]
  },
  {
    "Person Code": "0x2b",
    "Broker Data": "",
    "Name": "Tregona,Jaquenette",
    "Address": "8 Briar Crest Place",
    "Email Addresses": ["jtregona12@noaa.gov","jtregona12@java.com"]
  },
  {
    "Person Code": "0x2c",
    "Broker Data": "",
    "Name": "Hazelgrove,Waylan",
    "Address": "03030 Harper Way",
    "Email Addresses": ["whazelgrove13@goo.gl","whazelgrove13@samsung.com"]
  },
  {
    "Person Code": "0x2d",
    "Broker Data": "",
    "Name": "Sancias,Fifi",
    "Address": "0 Dakota Crossing",
    "Email Addresses": ["fsancias14@ovh.net","fsancias14@cdbaby.com"]
  },
  {
    "Person Code": "0x2e",
    "Broker Data": "",
    "Name": "Winsom,Nehemiah",
    "Address": "32642 Merrick Road",
    "Email Addresses": ["nwinsom15@facebook.com"]
  },
  {
    "Person Code": "0x2f",
    "Broker Data": "",
    "Name": "Brasier,Myrle",
    "Address": "633 Arrowood Park",
    "Email Addresses": ["mbrasier16@vk.com","mbrasier16@alexa.com"]
  },
  {
    "Person Code": "0x30",
    "Broker Data": "",
    "Name": "Cardoe,Standford",
    "Address": "1 Ilene Alley",
    "Email Addresses": ["scardoe17@theatlantic.com","scardoe17@indiatimes.com"]
  },
  {
    "Person Code": "0x31",
    "Broker Data": "",
    "Name": "Slopier,Fredia",
    "Address": "690 Redwing Trail",
    "Email Addresses": ["fslopier18@indiegogo.com"]
  },
  {
    "Person Code": "0x32",
    "Broker Data": "",
    "Name": "Hexter,Aldin",
    "Address": "168 Kenwood Circle",
    "Email Addresses": ["ahexter19@miibeian.gov.cn","ahexter19@a8.net"]
  },
  {
    "Person Code": "0x33",
    "Broker Data": "",
    "Name": "Timmis,Melany",
    "Address": "20 Di Loreto Street",
    "Email Addresses": ["mtimmis1a@msn.com","mtimmis1a@theatlantic.com"]
  },
  {
    "Person Code": "0x34",
    "Broker Data": "",
    "Name": "Monan,Gonzales",
    "Address": "8080 Redwing Road",
    "Email Addresses": ["gmonan1b@github.io"]
  },
  {
    "Person Code": "0x35",
    "Broker Data": "",
    "Name": "Greave,Herta",
    "Address": "457 Carberry Place",
    "Email Addresses": ["hgreave1c@is.gd","hgreave1c@mozilla.org"]
  },
  {
    "Person Code": "0x36",
    "Broker Data": "",
    "Name": "Brands,Celestina",
    "Address": "65 Fairfield Crossing",
    "Email Addresses": ["cbrands1d@so-net.ne.jp"]
  },
  {
    "Person Code": "0x37",
    "Broker Data": "",
    "Name": "Noone,Husein",
    "Address": "6 Starling Hill",
    "Email Addresses": ["hnoone1e@ovh.net","hnoone1e@huffingtonpost.com"]
  },
  {
    "Person Code": "0x38",
    "Broker Data": "",
    "Name": "Heald,Brenda",
    "Address": "84792 Mallard Point",
    "Email Addresses": ["bheald1f@washington.edu"]
  },
  {
    "Person Code": "0x39",
    "Broker Data": "",
    "Name": "Orgel,Rozanna",
    "Address": "5 Bartelt Alley",
    "Email Addresses": ["rorgel1g@addthis.com"]
  },
  {
    "Person Code": "0x3a",
    "Broker Data": "",
    "Name": "Leadbeater,Tadd",
    "Address": "3 Straubel Drive",
    "Email Addresses": ["tleadbeater1h@meetup.com"]
  },
  {
    "Person Code": "0x3b",
    "Broker Data": "",
    "Name": "Shakspeare,Hedi",
    "Address": "7521 Twin Pines Drive",
    "Email Addresses": ["hshakspeare1i@tamu.edu","hshakspeare1i@printfriendly.com"]
  },
  {
    "Person Code": "0x3c",
    "Broker Data": "",
    "Name": "Looks,Tania",
    "Address": "78839 Eagan Circle",
    "Email Addresses": ["tlooks1j@gov.uk","tlooks1j@unc.edu"]
  },
  {
    "Person Code": "0x3d",
    "Broker Data": "",
    "Name": "Thrasher,Irma",
    "Address": "21 Harbort Place",
    "Email Addresses": ["ithrasher1k@timesonline.co.uk"]
  },
  {
    "Person Code": "0x3e",
    "Broker Data": "",
    "Name": "Feltham,Axel",
    "Address": "16908 Ridgeview Drive",
    "Email Addresses": ["afeltham1l@4shared.com"]
  },
  {
    "Person Code": "0x3f",
    "Broker Data": "",
    "Name": "Johnsey,Lu",
    "Address": "6 Bellgrove Park",
    "Email Addresses": ["ljohnsey1m@about.com"]
  },
  {
    "Person Code": "0x40",
    "Broker Data": "J",
    "Name": "Bamforth,Francene",
    "Address": "6418 Hayes Plaza",
    "Email Addresses": [""]
  },
  {
    "Person Code": "0x41",
    "Broker Data": "",
    "Name": "Stedall,Danette",
    "Address": "9813 Golf Course Terrace",
    "Email Addresses": ["dstedall1o@ask.com"]
  },
  {
    "Person Code": "0x42",
    "Broker Data": "",
    "Name": "Docharty,Orelie",
    "Address": "4159 Sauthoff Pass",
    "Email Addresses": ["odocharty1p@tripadvisor.com"]
  },
  {
    "Person Code": "0x43",
    "Broker Data": "J",
    "Name": "Double,Catriona",
    "Address": "44591 Barby Junction",
    "Email Addresses": ["cdouble1q@naver.com","cdouble1q@ameblo.jp"]
  },
  {
    "Person Code": "0x44",
    "Broker Data": "",
    "Name": "Caress,Ashlen",
    "Address": "7 Swallow Way",
    "Email Addresses": ["acaress1r@sciencedirect.com","acaress1r@godaddy.com"]
  },
  {
    "Person Code": "0x45",
    "Broker Data": "",
    "Name": "Gainforth,Yolanda",
    "Address": "93984 Gerald Trail",
    "Email Addresses": [""]
  },
  {
    "Person Code": "0x46",
    "Broker Data": "",
    "Name": "Dallemore,Esra",
    "Address": "3266 Straubel Place",
    "Email Addresses": ["edallemore1t@google.it","edallemore1t@gizmodo.com"]
  },
  {
    "Person Code": "0x47",
    "Broker Data": "",
    "Name": "Fearick,Guendolen",
    "Address": "726 Cherokee Place",
    "Email Addresses": ["gfearick1u@google.ru"]
  },
  {
    "Person Code": "0x48",
    "Broker Data": "",
    "Name": "Paxton,Ber",
    "Address": "21 Haas Junction",
    "Email Addresses": ["bpaxton1v@webmd.com","bpaxton1v@lycos.com"]
  },
  {
    "Person Code": "0x49",
    "Broker Data": "",
    "Name": "Tarling,Dian",
    "Address": "3677 Boyd Avenue",
    "Email Addresses": ["dtarling1w@mapy.cz","dtarling1w@freewebs.com"]
  },
  {
    "Person Code": "0x4a",
    "Broker Data": "J",
    "Name": "Ivatt,Terri-jo",
    "Address": "69228 Lien Drive",
    "Email Addresses": ["tivatt1x@ebay.co.uk"]
  },
  {
    "Person Code": "0x4b",
    "Broker Data": "",
    "Name": "Ballston,Dorry",
    "Address": "357 Hanson Junction",
    "Email Addresses": ["dballston1y@wordpress.org"]
  },
  {
    "Person Code": "0x4c",
    "Broker Data": "",
    "Name": "Kersey,Merrili",
    "Address": "31 Hermina Junction",
    "Email Addresses": ["mkersey1z@bluehost.com"]
  },
  {
    "Person Code": "0x4d",
    "Broker Data": "",
    "Name": "Crumby,Aviva",
    "Address": "030 Kedzie Drive",
    "Email Addresses": ["acrumby20@bloomberg.com"]
  },
  {
    "Person Code": "0x4e",
    "Broker Data": "",
    "Name": "Mantle,Cloe",
    "Address": "78 Del Mar Pass",
    "Email Addresses": ["cmantle21@indiatimes.com","cmantle21@printfriendly.com"]
  },
  {
    "Person Code": "0x4f",
    "Broker Data": "",
    "Name": "Hargreves,Hamlen",
    "Address": "1 Almo Way",
    "Email Addresses": ["hhargreves22@soup.io","hhargreves22@friendfeed.com"]
  },
  {
    "Person Code": "0x50",
    "Broker Data": "",
    "Name": "Prime,Annabela",
    "Address": "23 Esch Drive",
    "Email Addresses": ["aprime23@nih.gov"]
  },
  {
    "Person Code": "0x51",
    "Broker Data": "",
    "Name": "Himpson,Jessie",
    "Address": "81 Summerview Parkway",
    "Email Addresses": ["jhimpson24@cyberchimps.com"]
  },
  {
    "Person Code": "0x52",
    "Broker Data": "J",
    "Name": "Grigolon,Wakefield",
    "Address": "8 Rutledge Drive",
    "Email Addresses": ["wgrigolon25@partyhatsforfree.com","wgrigolon25@lulu.com"]
  },
  {
    "Person Code": "0x53",
    "Broker Data": "",
    "Name": "Scotchmoor,Elyse",
    "Address": "64 Homewood Street",
    "Email Addresses": ["escotchmoor26@businessweek.com"]
  },
  {
    "Person Code": "0x54",
    "Broker Data": "J",
    "Name": "Attersoll,Sashenka",
    "Address": "98 Eagle Crest Court",
    "Email Addresses": ["sattersoll27@yale.edu","sattersoll27@bbb.org"]
  },
  {
    "Person Code": "0x55",
    "Broker Data": "J",
    "Name": "Darracott,Virgil",
    "Address": "50 Myrtle Court",
    "Email Addresses": ["vdarracott28@stanford.edu"]
  },
  {
    "Person Code": "0x56",
    "Broker Data": "",
    "Name": "Dearsley,Sibelle",
    "Address": "9 Lawn Terrace",
    "Email Addresses": ["sdearsley29@nature.com"]
  },
  {
    "Person Code": "0x57",
    "Broker Data": "",
    "Name": "Entwistle,Gussi",
    "Address": "5957 Esker Road",
    "Email Addresses": ["gentwistle2a@ask.com"]
  },
  {
    "Person Code": "0x58",
    "Broker Data": "",
    "Name": "Neylon,Audre",
    "Address": "705 Arkansas Center",
    "Email Addresses": ["aneylon2b@discuz.net"]
  },
  {
    "Person Code": "0x59",
    "Broker Data": "",
    "Name": "Jodrelle,Crawford",
    "Address": "755 Huxley Plaza",
    "Email Addresses": ["cjodrelle2c@last.fm"]
  },
  {
    "Person Code": "0x5a",
    "Broker Data": "",
    "Name": "Keedwell,Dory",
    "Address": "0191 Myrtle Trail",
    "Email Addresses": ["dkeedwell2d@homestead.com","dkeedwell2d@bigcartel.com"]
  },
  {
    "Person Code": "0x5b",
    "Broker Data": "",
    "Name": "McAlpin,Hewet",
    "Address": "259 Kipling Road",
    "Email Addresses": ["hmcalpin2e@behance.net","hmcalpin2e@amazonaws.com"]
  },
  {
    "Person Code": "0x5c",
    "Broker Data": "",
    "Name": "Mabbitt,Elvira",
    "Address": "351 Anderson Crossing",
    "Email Addresses": ["emabbitt2f@vimeo.com"]
  },
  {
    "Person Code": "0x5d",
    "Broker Data": "E",
    "Name": "MacMenamy,Juliana",
    "Address": "898 Kim Park",
    "Email Addresses": ["jmacmenamy2g@mapquest.com","jmacmenamy2g@cocolog-nifty.com"]
  },
  {
    "Person Code": "0x5e",
    "Broker Data": "",
    "Name": "Peagrim,Marty",
    "Address": "482 Southridge Place",
    "Email Addresses": ["mpeagrim2h@csmonitor.com"]
  },
  {
    "Person Code": "0x5f",
    "Broker Data": "",
    "Name": "Foucar,Wilmar",
    "Address": "454 Jackson Alley",
    "Email Addresses": ["wfoucar2i@weibo.com"]
  },
  {
    "Person Code": "0x60",
    "Broker Data": "",
    "Name": "Gilphillan,Sheelah",
    "Address": "62879 Meadow Vale Junction",
    "Email Addresses": ["sgilphillan2j@mlb.com"]
  },
  {
    "Person Code": "0x61",
    "Broker Data": "",
    "Name": "Brettor,Maye",
    "Address": "7 Corry Court",
    "Email Addresses": ["mbrettor2k@oracle.com"]
  },
  {
    "Person Code": "0x62",
    "Broker Data": "",
    "Name": "D'orsay,Haley",
    "Address": "5 Elgar Point",
    "Email Addresses": ["hdorsay2l@noaa.gov"]
  },
  {
    "Person Code": "0x63",
    "Broker Data": "",
    "Name": "Scurr,Cly",
    "Address": "02540 Lunder Crossing",
    "Email Addresses": ["cscurr2m@eventbrite.com"]
  },
  {
    "Person Code": "0x64",
    "Broker Data": "",
    "Name": "Jull,Elladine",
    "Address": "4 Monument Street",
    "Email Addresses": ["ejull2n@adobe.com"]
  },
  {
    "Person Code": "0x65",
    "Broker Data": "E",
    "Name": "Bullan,Frederic",
    "Address": "8 Sullivan Lane",
    "Email Addresses": ["fbullan2o@ycombinator.com","fbullan2o@zdnet.com"]
  },
  {
    "Person Code": "0x66",
    "Broker Data": "E",
    "Name": "Maker,Ewell",
    "Address": "347 Springs Avenue",
    "Email Addresses": ["emaker2p@taobao.com"]
  },
  {
    "Person Code": "0x67",
    "Broker Data": "",
    "Name": "Arnowitz,Xenos",
    "Address": "073 Sullivan Alley",
    "Email Addresses": ["xarnowitz2q@instagram.com"]
  },
  {
    "Person Code": "0x68",
    "Broker Data": "E",
    "Name": "Le Breton,Alisander",
    "Address": "810 Kinsman Hill",
    "Email Addresses": ["alebreton2r@unc.edu","alebreton2r@jimdo.com"]
  }
]